pythoc/__init__.py
pythoc/cimport.py
pythoc/compiler.py
pythoc/context.py
pythoc/effect.py
pythoc/forward_ref.py
pythoc/ir_helpers.py
pythoc/llvm_extensions.py
pythoc/logger.py
pythoc/native_executor.py
pythoc/registry.py
pythoc/scope_manager.py
pythoc/type_check.py
pythoc/type_converter.py
pythoc/type_id.py
pythoc/type_resolver.py
pythoc/valueref.py
pythoc/ast_visitor/__init__.py
pythoc/ast_visitor/assignments.py
pythoc/ast_visitor/base.py
pythoc/ast_visitor/calls.py
pythoc/ast_visitor/control_flow_builder.py
pythoc/ast_visitor/expressions.py
pythoc/ast_visitor/functions.py
pythoc/ast_visitor/helpers.py
pythoc/ast_visitor/statements.py
pythoc/ast_visitor/stmt_control.py
pythoc/ast_visitor/stmt_if.py
pythoc/ast_visitor/stmt_loops.py
pythoc/ast_visitor/stmt_match.py
pythoc/ast_visitor/subscripts.py
pythoc/ast_visitor/varargs.py
pythoc/ast_visitor/visitor_impl.py
pythoc/ast_visitor/yield_transform.py
pythoc/backend/__init__.py
pythoc/backend/abstract.py
pythoc/backend/constexpr_backend.py
pythoc/backend/llvm_backend.py
pythoc/bindings/__init__.py
pythoc/bindings/bindgen.py
pythoc/bindings/c_ast.py
pythoc/bindings/c_parser.py
pythoc/bindings/c_token.py
pythoc/bindings/lexer.py
pythoc/bindings/pythoc_backend.py
pythoc/build/__init__.py
pythoc/build/cache.py
pythoc/build/output_manager.py
pythoc/builder/__init__.py
pythoc/builder/abstract.py
pythoc/builder/llvm_c_builder.py
pythoc/builder/llvm_simple_builder.py
pythoc/builder/null_builder.py
pythoc/builder/abi/__init__.py
pythoc/builder/abi/aarch64.py
pythoc/builder/abi/base.py
pythoc/builder/abi/coercion.py
pythoc/builder/abi/x86_64.py
pythoc/builtin_entities/__init__.py
pythoc/builtin_entities/array.py
pythoc/builtin_entities/assume.py
pythoc/builtin_entities/base.py
pythoc/builtin_entities/char.py
pythoc/builtin_entities/composite_base.py
pythoc/builtin_entities/consume.py
pythoc/builtin_entities/defer.py
pythoc/builtin_entities/enum.py
pythoc/builtin_entities/func.py
pythoc/builtin_entities/intrinsics.py
pythoc-0.3.1.dist-info/licenses/LICENSE
pythoc-0.3.1.dist-info/METADATA
pythoc-0.3.1.dist-info/WHEEL
pythoc-0.3.1.dist-info/top_level.txt
pythoc-0.3.1.dist-info/RECORD
