Metadata-Version: 2.4
Name: pythoc
Version: 0.3.1
Summary: PythoC: A Python DSL compiler that maps statically-typed Python subset to LLVM IR, providing C-equivalent capabilities with Python syntax
Home-page: https://github.com/1flei/PythoC
Author: PythoC Compiler Team
License: MIT
Project-URL: Homepage, https://github.com/1flei/PythoC
Project-URL: Repository, https://github.com/1flei/PythoC
Project-URL: Documentation, https://github.com/1flei/PythoC/blob/master/README.md
Keywords: compiler,llvm,python,static-typing,code-generation
Classifier: Development Status :: 3 - Alpha
Classifier: Intended Audience :: Developers
Classifier: License :: OSI Approved :: MIT License
Classifier: Programming Language :: Python :: 3
Classifier: Programming Language :: Python :: 3.10
Classifier: Programming Language :: Python :: 3.11
Classifier: Programming Language :: Python :: 3.12
Classifier: Topic :: Software Development :: Compilers
Classifier: Topic :: Software Development :: Code Generators
Requires-Python: >=3.8
License-File: LICENSE
Requires-Dist: llvmlite<0.45.0,>=0.40.0
Provides-Extra: dev
Requires-Dist: pytest>=7.0.0; extra == "dev"
Requires-Dist: pytest-cov>=4.0.0; extra == "dev"
Dynamic: home-page
Dynamic: license-file
Dynamic: requires-python
